[{"puzzleId":"03nTL","fen":"8/8/8/5p2/8/3k1K2/3np3/R7 w - - 2 75","sideToMove":"w","rating":2349,"pieceCount":6,"whitePieces":["Kf3","Ra1"],"blackPieces":["Kd3","Nd2","Pe2","Pf5"],"continuationSan":["Kf4","Nb3","Rb1","Nd4"],"continuationText":"75. Kf4 75... Nb3 76. Rb1 76... Nd4","themes":["crushing","defensiveMove","endgame","master","short"],"source":"local_db"},{"puzzleId":"04b9O","fen":"8/8/6p1/1p1K4/5k2/8/1PP5/8 w - - 1 42","sideToMove":"w","rating":2327,"pieceCount":6,"whitePieces":["Kd5","Pb2","Pc2"],"blackPieces":["Kf4","Pb5","Pg6"],"continuationSan":["b3","b4","Kd4","g5"],"continuationText":"42. b3 42... b4 43. Kd4 43... g5","themes":["crushing","defensiveMove","endgame","pawnEndgame","quietMove","short"],"source":"local_db"},{"puzzleId":"05RqS","fen":"5QK1/8/8/8/8/2k5/3p4/3r4 w - - 0 65","sideToMove":"w","rating":2360,"pieceCount":5,"whitePieces":["Kg8","Qf8"],"blackPieces":["Kc3","Rd1","Pd2"],"continuationSan":["Kh7","Rh1+","Kg8","Rg1+"],"continuationText":"65. Kh7 65... Rh1+ 66. Kg8 66... Rg1+","themes":["crushing","endgame","master","queenRookEndgame","short"],"source":"local_db"},{"puzzleId":"09VoA","fen":"8/8/3r4/4kp2/7R/2K5/7P/8 w - - 0 56","sideToMove":"w","rating":2376,"pieceCount":6,"whitePieces":["Kc3","Rh4","Ph2"],"blackPieces":["Ke5","Rd6","Pf5"],"continuationSan":["Rh3","Ke4","Rh8","f4"],"continuationText":"56. Rh3 56... Ke4 57. Rh8 57... f4","themes":["advantage","defensiveMove","endgame","rookEndgame","short"],"source":"local_db"},{"puzzleId":"09rQA","fen":"8/1r6/2PK4/3Pp3/4k3/8/8/8 b - - 0 61","sideToMove":"b","rating":2392,"pieceCount":6,"whitePieces":["Kd6","Pc6","Pd5"],"blackPieces":["Ke4","Rb7","Pe5"],"continuationSan":["Rb4","Kc5","Rd4","c7"],"continuationText":"61... Rb4 62. Kc5 62... Rd4 63. c7","themes":["advancedPawn","advantage","endgame","master","rookEndgame","short"],"source":"local_db"},{"puzzleId":"0FmyL","fen":"1R6/7p/5P2/1pk1K3/7r/8/8/8 b - - 0 55","sideToMove":"b","rating":2344,"pieceCount":7,"whitePieces":["Ke5","Rb8","Pf6"],"blackPieces":["Kc5","Rh4","Pb5","Ph7"],"continuationSan":["Rh1","Rc8+","Kb4","f7"],"continuationText":"55... Rh1 56. Rc8+ 56... Kb4 57. f7","themes":["advancedPawn","crushing","endgame","rookEndgame","short"],"source":"local_db"},{"puzzleId":"0JLkI","fen":"7R/8/8/8/8/3npk2/1p5P/1K6 w - - 0 55","sideToMove":"w","rating":2389,"pieceCount":7,"whitePieces":["Kb1","Rh8","Ph2"],"blackPieces":["Kf3","Nd3","Pb2","Pe3"],"continuationSan":["Rf8+","Ke4","Rf1","e2"],"continuationText":"55. Rf8+ 55... Ke4 56. Rf1 56... e2","themes":["advancedPawn","crushing","defensiveMove","endgame","master","short"],"source":"local_db"},{"puzzleId":"0JN6A","fen":"8/7R/8/8/8/1r1PK1k1/7p/8 w - - 0 60","sideToMove":"w","rating":2308,"pieceCount":6,"whitePieces":["Ke3","Rh7","Pd3"],"blackPieces":["Kg3","Rb3","Ph2"],"continuationSan":["Ke4","Rb1","Rxh2","Kxh2"],"continuationText":"60. Ke4 60... Rb1 61. Rxh2 61... Kxh2","themes":["crushing","endgame","master","quietMove","rookEndgame","short"],"source":"local_db"},{"puzzleId":"0MTmN","fen":"8/1R6/rp3k2/8/1KP5/8/8/8 b - - 4 50","sideToMove":"b","rating":2335,"pieceCount":6,"whitePieces":["Kb4","Rb7","Pc4"],"blackPieces":["Kf6","Ra6","Pb6"],"continuationSan":["Ke6","Kb5","Ra1","Kxb6"],"continuationText":"50... Ke6 51. Kb5 51... Ra1 52. Kxb6","themes":["crushing","endgame","rookEndgame","short"],"source":"local_db"},{"puzzleId":"0VY8v","fen":"4R3/8/8/2k1p3/2r5/1p2KP2/8/8 w - - 0 57","sideToMove":"w","rating":2322,"pieceCount":7,"whitePieces":["Ke3","Re8","Pf3"],"blackPieces":["Kc5","Rc4","Pb3","Pe5"],"continuationSan":["Rxe5+","Kb4","Kd2","Rc2+"],"continuationText":"57. Rxe5+ 57... Kb4 58. Kd2 58... Rc2+","themes":["crushing","defensiveMove","endgame","rookEndgame","short"],"source":"local_db"},{"puzzleId":"0VluM","fen":"8/1p3k2/2p5/6K1/P5P1/8/8/8 b - - 0 51","sideToMove":"b","rating":2399,"pieceCount":6,"whitePieces":["Kg5","Pa4","Pg4"],"blackPieces":["Kf7","Pb7","Pc6"],"continuationSan":["c5","a5","c4","Kf4"],"continuationText":"51... c5 52. a5 52... c4 53. Kf4","themes":["crushing","defensiveMove","endgame","pawnEndgame","quietMove","short"],"source":"local_db"},{"puzzleId":"0WjZe","fen":"4K3/4P1k1/8/8/8/2R5/2p5/2r5 b - - 2 59","sideToMove":"b","rating":2382,"pieceCount":6,"whitePieces":["Ke8","Rc3","Pe7"],"blackPieces":["Kg7","Rc1","Pc2"],"continuationSan":["Kf6","Kf8","Rh1","Rc6+"],"continuationText":"59... Kf6 60. Kf8 60... Rh1 61. Rc6+","themes":["crushing","endgame","master","rookEndgame","short"],"source":"local_db"}]