[{"puzzleId": "VweKL", "fen": "6Q1/5K2/1p1r2pk/8/5b1P/8/8/8 w - - 2 47", "sideToMove": "w", "pieceCount": 8, "ratingBucket": 1400, "whitePieces": ["Kf7", "Qg8", "Ph4"], "blackPieces": ["Kh6", "Rd6", "Bf4", "Pb6", "Pg6"], "continuationSan": ["Qh8#"], "continuationText": "47. Qh8#", "themes": ["endgame", "mate", "mateIn1", "oneMove"], "source": "lichess_static"}, {"puzzleId": "0ZsPp", "fen": "8/R7/3k4/3p3p/2p5/7r/1K1R4/8 b - - 1 52", "sideToMove": "b", "pieceCount": 8, "ratingBucket": 1400, "whitePieces": ["Kb2", "Ra7", "Rd2"], "blackPieces": ["Kd6", "Rh3", "Pc4", "Pd5", "Ph5"], "continuationSan": ["c3+", "Kc2", "cxd2"], "continuationText": "52... c3+ 53. Kc2 cxd2", "themes": ["advancedPawn", "crushing", "endgame", "fork", "rookEndgame", "short"], "source": "lichess_static"}, {"puzzleId": "16MfV", "fen": "8/2P5/b2R4/4p3/1r2k3/8/3K1P2/8 w - - 1 44", "sideToMove": "w", "pieceCount": 8, "ratingBucket": 1400, "whitePieces": ["Kd2", "Rd6", "Pc7", "Pf2"], "blackPieces": ["Ke4", "Rb4", "Ba6", "Pe5"], "continuationSan": ["Rxa6", "Rc4", "Ra4"], "continuationText": "44. Rxa6 Rc4 45. Ra4", "themes": ["crushing", "endgame", "hangingPiece", "pin", "short"], "source": "lichess_static"}, {"puzzleId": "W74LU", "fen": "8/8/8/8/1k3K2/4QPP1/2r3P1/1q6 w - - 4 62", "sideToMove": "w", "pieceCount": 8, "ratingBucket": 1400, "whitePieces": ["Kf4", "Qe3", "Pf3", "Pg2", "Pg3"], "blackPieces": ["Kb4", "Qb1", "Rc2"], "continuationSan": ["Qb6+", "Kc3", "Qxb1"], "continuationText": "62. Qb6+ Kc3 63. Qxb1", "themes": ["crushing", "endgame", "short", "skewer"], "source": "lichess_static"}, {"puzzleId": "OFnSK", "fen": "8/5k2/4pP2/6B1/1n5P/K7/2p5/8 w - - 0 51", "sideToMove": "w", "pieceCount": 8, "ratingBucket": 1400, "whitePieces": ["Ka3", "Bg5", "Pf6", "Ph4"], "blackPieces": ["Kf7", "Nb4", "Pc2", "Pe6"], "continuationSan": ["Kxb4", "c1=Q", "Bxc1"], "continuationText": "51. Kxb4 c1=Q 52. Bxc1", "themes": ["crushing", "endgame", "hangingPiece", "short"], "source": "lichess_static"}, {"puzzleId": "WWZ68", "fen": "8/6p1/3k2K1/6B1/8/4R1P1/6r1/2q5 w - - 0 49", "sideToMove": "w", "pieceCount": 8, "ratingBucket": 1400, "whitePieces": ["Kg6", "Re3", "Bg5", "Pg3"], "blackPieces": ["Kd6", "Qc1", "Rg2", "Pg7"], "continuationSan": ["Rd3+", "Ke5", "Bxc1"], "continuationText": "49. Rd3+ Ke5 50. Bxc1", "themes": ["crushing", "discoveredAttack", "endgame", "short"], "source": "lichess_static"}, {"puzzleId": "40wEu", "fen": "8/8/8/4kp1p/5n1P/4K3/4p3/4N3 w - - 2 55", "sideToMove": "w", "pieceCount": 8, "ratingBucket": 1400, "whitePieces": ["Ke3", "Ne1", "Ph4"], "blackPieces": ["Ke5", "Nf4", "Pe2", "Pf5", "Ph5"], "continuationSan": ["Nf3+", "Ke6", "Kxf4"], "continuationText": "55. Nf3+ Ke6 56. Kxf4", "themes": ["crushing", "deflection", "endgame", "knightEndgame", "short"], "source": "lichess_static"}, {"puzzleId": "8AAe8", "fen": "8/6p1/3k4/3rp3/8/P1R1K3/6P1/8 w - - 1 52", "sideToMove": "w", "pieceCount": 8, "ratingBucket": 1400, "whitePieces": ["Ke3", "Rc3", "Pa3", "Pg2"], "blackPieces": ["Kd6", "Rd5", "Pe5", "Pg7"], "continuationSan": ["Rd3"], "continuationText": "52. Rd3", "themes": ["crushing", "endgame", "oneMove", "rookEndgame"], "source": "lichess_static"}, {"puzzleId": "6WG96", "fen": "q7/7p/2N1N1p1/3K1k2/4R3/8/8/8 w - - 8 57", "sideToMove": "w", "pieceCount": 8, "ratingBucket": 1400, "whitePieces": ["Kd5", "Re4", "Nc6", "Ne6"], "blackPieces": ["Kf5", "Qa8", "Pg6", "Ph7"], "continuationSan": ["Rf4#"], "continuationText": "57. Rf4#", "themes": ["endgame", "mate", "mateIn1", "oneMove"], "source": "lichess_static"}, {"puzzleId": "MLBsE", "fen": "1k6/3R4/P5p1/1bb5/7P/5K2/8/8 w - - 1 58", "sideToMove": "w", "pieceCount": 8, "ratingBucket": 1400, "whitePieces": ["Kf3", "Rd7", "Pa6", "Ph4"], "blackPieces": ["Kb8", "Bb5", "Bc5", "Pg6"], "continuationSan": ["Rb7+", "Ka8", "Rxb5"], "continuationText": "58. Rb7+ Ka8 59. Rxb5", "themes": ["crushing", "endgame", "fork", "short"], "source": "lichess_static"}, {"puzzleId": "WYeNf", "fen": "8/4k3/7R/R7/P3K3/2p5/8/2rq4 w - - 0 53", "sideToMove": "w", "pieceCount": 8, "ratingBucket": 1400, "whitePieces": ["Ke4", "Ra5", "Rh6", "Pa4"], "blackPieces": ["Ke7", "Qd1", "Rc1", "Pc3"], "continuationSan": ["Ra7+", "Qd7", "Rh7+"], "continuationText": "53. Ra7+ Qd7 54. Rh7+", "themes": ["crushing", "endgame", "pin", "queenRookEndgame", "short"], "source": "lichess_static"}, {"puzzleId": "WHl2H", "fen": "8/8/7B/3k1P2/2p5/b3K3/P6P/8 b - - 0 40", "sideToMove": "b", "pieceCount": 8, "ratingBucket": 1400, "whitePieces": ["Ke3", "Bh6", "Pa2", "Pf5", "Ph2"], "blackPieces": ["Kd5", "Ba3", "Pc4"], "continuationSan": ["Bc1+", "Ke2", "Bxh6"], "continuationText": "40... Bc1+ 41. Ke2 Bxh6", "themes": ["bishopEndgame", "crushing", "endgame", "short", "skewer"], "source": "lichess_static"}, {"puzzleId": "N4cI7", "fen": "8/8/4p3/3p1p2/3P1K2/4rN1k/8/8 w - - 0 68", "sideToMove": "w", "pieceCount": 8, "ratingBucket": 1400, "whitePieces": ["Kf4", "Nf3", "Pd4"], "blackPieces": ["Kh3", "Re3", "Pd5", "Pe6", "Pf5"], "continuationSan": ["Kxe3", "Kg4", "Ne5+"], "continuationText": "68. Kxe3 Kg4 69. Ne5+", "themes": ["crushing", "endgame", "hangingPiece", "short"], "source": "lichess_static"}, {"puzzleId": "6L5qT", "fen": "8/2k5/8/1R1P3r/1PK5/2P5/3r4/8 w - - 9 56", "sideToMove": "w", "pieceCount": 8, "ratingBucket": 1400, "whitePieces": ["Kc4", "Rb5", "Pb4", "Pc3", "Pd5"], "blackPieces": ["Kc7", "Rd2", "Rh5"], "continuationSan": ["d6+", "Kc6", "Rxh5"], "continuationText": "56. d6+ Kc6 57. Rxh5", "themes": ["crushing", "discoveredAttack", "endgame", "rookEndgame", "short"], "source": "lichess_static"}, {"puzzleId": "NBknZ", "fen": "8/7P/5R2/8/3k1p1r/2p5/6P1/6K1 w - - 0 58", "sideToMove": "w", "pieceCount": 8, "ratingBucket": 1400, "whitePieces": ["Kg1", "Rf6", "Pg2", "Ph7"], "blackPieces": ["Kd4", "Rh4", "Pc3", "Pf4"], "continuationSan": ["Rxf4+", "Rxf4", "h8=Q+"], "continuationText": "58. Rxf4+ Rxf4 59. h8=Q+", "themes": ["advancedPawn", "advantage", "deflection", "endgame", "promotion", "rookEndgame", "short"], "source": "lichess_static"}, {"puzzleId": "QHzrS", "fen": "6n1/5p2/8/6Kp/5P2/5k1P/7B/8 b - - 15 50", "sideToMove": "b", "pieceCount": 8, "ratingBucket": 1400, "whitePieces": ["Kg5", "Bh2", "Pf4", "Ph3"], "blackPieces": ["Kf3", "Ng8", "Pf7", "Ph5"], "continuationSan": ["Kg2", "Kxh5", "Kxh2"], "continuationText": "50... Kg2 51. Kxh5 Kxh2", "themes": ["crushing", "endgame", "short", "trappedPiece"], "source": "lichess_static"}, {"puzzleId": "KPGB7", "fen": "k7/8/1R6/4R2p/7r/2K2P2/6r1/8 w - - 0 44", "sideToMove": "w", "pieceCount": 8, "ratingBucket": 1400, "whitePieces": ["Kc3", "Rb6", "Re5", "Pf3"], "blackPieces": ["Ka8", "Rg2", "Rh4", "Ph5"], "continuationSan": ["Ra5#"], "continuationText": "44. Ra5#", "themes": ["endgame", "mate", "mateIn1", "oneMove", "rookEndgame"], "source": "lichess_static"}, {"puzzleId": "8qroL", "fen": "5R2/8/8/8/P3K3/3p4/2rkn3/1R6 b - - 0 53", "sideToMove": "b", "pieceCount": 8, "ratingBucket": 1400, "whitePieces": ["Ke4", "Rb1", "Rf8", "Pa4"], "blackPieces": ["Kd2", "Rc2", "Ne2", "Pd3"], "continuationSan": ["Nc3+", "Kd4", "Nxb1"], "continuationText": "53... Nc3+ 54. Kd4 Nxb1", "themes": ["crushing", "endgame", "fork", "short"], "source": "lichess_static"}, {"puzzleId": "9FJHL", "fen": "8/8/5p2/8/2k1P3/2q5/2p4R/1K1R4 w - - 0 60", "sideToMove": "w", "pieceCount": 8, "ratingBucket": 1400, "whitePieces": ["Kb1", "Rd1", "Rh2", "Pe4"], "blackPieces": ["Kc4", "Qc3", "Pc2", "Pf6"], "continuationSan": ["Rxc2", "Kb3", "Rxc3+"], "continuationText": "60. Rxc2 Kb3 61. Rxc3+", "themes": ["crushing", "endgame", "pin", "queenRookEndgame", "short"], "source": "lichess_static"}, {"puzzleId": "1E70T", "fen": "8/r7/P3k3/5p2/1R6/5r2/R2K4/8 b - - 1 48", "sideToMove": "b", "pieceCount": 8, "ratingBucket": 1400, "whitePieces": ["Kd2", "Ra2", "Rb4", "Pa6"], "blackPieces": ["Ke6", "Ra7", "Rf3", "Pf5"], "continuationSan": ["Rf2+", "Ke3", "Rxa2"], "continuationText": "48... Rf2+ 49. Ke3 Rxa2", "themes": ["crushing", "endgame", "rookEndgame", "short", "skewer"], "source": "lichess_static"}, {"puzzleId": "OUSFh", "fen": "5K2/7P/5b1n/1k6/6p1/8/1p6/5R2 w - - 0 65", "sideToMove": "w", "pieceCount": 8, "ratingBucket": 1400, "whitePieces": ["Kf8", "Rf1", "Ph7"], "blackPieces": ["Kb5", "Bf6", "Nh6", "Pb2", "Pg4"], "continuationSan": ["Rxf6", "b1=Q", "h8=Q"], "continuationText": "65. Rxf6 b1=Q 66. h8=Q", "themes": ["advancedPawn", "crushing", "endgame", "hangingPiece", "promotion", "short"], "source": "lichess_static"}, {"puzzleId": "NgJky", "fen": "8/4k3/rB3R2/b2p1K2/3P4/8/8/8 w - - 2 59", "sideToMove": "w", "pieceCount": 8, "ratingBucket": 1400, "whitePieces": ["Kf5", "Rf6", "Bb6", "Pd4"], "blackPieces": ["Ke7", "Ra6", "Ba5", "Pd5"], "continuationSan": ["Bc5+", "Kd7", "Rxa6"], "continuationText": "59. Bc5+ Kd7 60. Rxa6", "themes": ["crushing", "discoveredAttack", "endgame", "short"], "source": "lichess_static"}, {"puzzleId": "Nwn42", "fen": "3r4/k7/8/1RKN4/4P3/1r3P2/8/8 b - - 0 41", "sideToMove": "b", "pieceCount": 8, "ratingBucket": 1400, "whitePieces": ["Kc5", "Rb5", "Nd5", "Pe4", "Pf3"], "blackPieces": ["Ka7", "Rb3", "Rd8"], "continuationSan": ["Rc8+", "Kd4", "Rxb5"], "continuationText": "41... Rc8+ 42. Kd4 Rxb5", "themes": ["crushing", "deflection", "endgame", "short"], "source": "lichess_static"}, {"puzzleId": "OSuvA", "fen": "5k2/5p1R/1r5p/8/6P1/7P/8/7K b - - 0 40", "sideToMove": "b", "pieceCount": 8, "ratingBucket": 1400, "whitePieces": ["Kh1", "Rh7", "Pg4", "Ph3"], "blackPieces": ["Kf8", "Rb6", "Pf7", "Ph6"], "continuationSan": ["Kg8", "Rxh6", "Rxh6"], "continuationText": "40... Kg8 41. Rxh6 Rxh6", "themes": ["crushing", "endgame", "rookEndgame", "short", "trappedPiece"], "source": "lichess_static"}, {"puzzleId": "FXEX9", "fen": "8/6R1/8/8/3B3p/4Pq1k/5P2/5K2 b - - 3 51", "sideToMove": "b", "pieceCount": 8, "ratingBucket": 1400, "whitePieces": ["Kf1", "Rg7", "Bd4", "Pe3", "Pf2"], "blackPieces": ["Kh3", "Qf3", "Ph4"], "continuationSan": ["Qd1#"], "continuationText": "51... Qd1#", "themes": ["endgame", "mate", "mateIn1", "oneMove"], "source": "lichess_static"}, {"puzzleId": "IVLoE", "fen": "8/7p/7k/3Npp2/7r/3K4/8/6R1 b - - 8 46", "sideToMove": "b", "pieceCount": 8, "ratingBucket": 1400, "whitePieces": ["Kd3", "Rg1", "Nd5"], "blackPieces": ["Kh6", "Rh4", "Pe5", "Pf5", "Ph7"], "continuationSan": ["Rd4+", "Ke3", "Rxd5"], "continuationText": "46... Rd4+ 47. Ke3 Rxd5", "themes": ["crushing", "endgame", "fork", "short"], "source": "lichess_static"}, {"puzzleId": "YYKvp", "fen": "8/4P3/7R/p7/2k1r2p/8/1P6/1K6 w - - 3 45", "sideToMove": "w", "pieceCount": 8, "ratingBucket": 1400, "whitePieces": ["Kb1", "Rh6", "Pb2", "Pe7"], "blackPieces": ["Kc4", "Re4", "Pa5", "Ph4"], "continuationSan": ["Rxh4", "Rxh4", "e8=Q"], "continuationText": "45. Rxh4 Rxh4 46. e8=Q", "themes": ["advancedPawn", "crushing", "deflection", "endgame", "pin", "promotion", "rookEndgame", "short"], "source": "lichess_static"}, {"puzzleId": "J3qE3", "fen": "6r1/2b5/8/2R4K/1p4p1/1k6/8/7R b - - 3 47", "sideToMove": "b", "pieceCount": 8, "ratingBucket": 1400, "whitePieces": ["Kh5", "Rc5", "Rh1"], "blackPieces": ["Kb3", "Rg8", "Bc7", "Pb4", "Pg4"], "continuationSan": ["Rh8+", "Kxg4", "Rxh1"], "continuationText": "47... Rh8+ 48. Kxg4 Rxh1", "themes": ["crushing", "endgame", "short", "skewer"], "source": "lichess_static"}, {"puzzleId": "3Ahw0", "fen": "8/8/5k2/2p1p3/4n1K1/3PN1p1/8/8 w - - 0 66", "sideToMove": "w", "pieceCount": 8, "ratingBucket": 1400, "whitePieces": ["Kg4", "Ne3", "Pd3"], "blackPieces": ["Kf6", "Ne4", "Pc5", "Pe5", "Pg3"], "continuationSan": ["dxe4", "g2", "Nxg2"], "continuationText": "66. dxe4 g2 67. Nxg2", "themes": ["crushing", "endgame", "hangingPiece", "knightEndgame", "short"], "source": "lichess_static"}, {"puzzleId": "CK3a5", "fen": "8/8/5k2/R4p1r/4p3/4P1K1/4P3/8 b - - 3 42", "sideToMove": "b", "pieceCount": 8, "ratingBucket": 1400, "whitePieces": ["Kg3", "Ra5", "Pe2", "Pe3"], "blackPieces": ["Kf6", "Rh5", "Pe4", "Pf5"], "continuationSan": ["f4+", "Kxf4", "Rxa5"], "continuationText": "42... f4+ 43. Kxf4 Rxa5", "themes": ["crushing", "discoveredAttack", "endgame", "rookEndgame", "short"], "source": "lichess_static"}, {"puzzleId": "ZIsUj", "fen": "R7/P7/8/6pp/6k1/r5P1/7K/8 b - - 0 41", "sideToMove": "b", "pieceCount": 8, "ratingBucket": 1400, "whitePieces": ["Kh2", "Ra8", "Pa7", "Pg3"], "blackPieces": ["Kg4", "Ra3", "Pg5", "Ph5"], "continuationSan": ["Ra2+", "Kg1", "Kxg3"], "continuationText": "41... Ra2+ 42. Kg1 Kxg3", "themes": ["crushing", "deflection", "endgame", "rookEndgame", "short"], "source": "lichess_static"}, {"puzzleId": "S2krj", "fen": "8/8/Rpk5/8/PrPKP3/8/8/8 b - - 0 42", "sideToMove": "b", "pieceCount": 8, "ratingBucket": 1400, "whitePieces": ["Kd4", "Ra6", "Pa4", "Pc4", "Pe4"], "blackPieces": ["Kc6", "Rb4", "Pb6"], "continuationSan": ["Kb7", "a5", "Kxa6"], "continuationText": "42... Kb7 43. a5 Kxa6", "themes": ["crushing", "endgame", "rookEndgame", "short", "trappedPiece"], "source": "lichess_static"}, {"puzzleId": "8VHzI", "fen": "6k1/6p1/p2QK3/4P3/1P6/8/8/5q2 b - - 8 53", "sideToMove": "b", "pieceCount": 8, "ratingBucket": 1400, "whitePieces": ["Ke6", "Qd6", "Pb4", "Pe5"], "blackPieces": ["Kg8", "Qf1", "Pa6", "Pg7"], "continuationSan": ["Qf7#"], "continuationText": "53... Qf7#", "themes": ["endgame", "mate", "mateIn1", "oneMove", "queenEndgame"], "source": "lichess_static"}, {"puzzleId": "QhQH9", "fen": "8/8/2Q1b1k1/1P6/5nPK/1r6/8/8 w - - 7 56", "sideToMove": "w", "pieceCount": 8, "ratingBucket": 1400, "whitePieces": ["Kh4", "Qc6", "Pb5", "Pg4"], "blackPieces": ["Kg6", "Rb3", "Be6", "Nf4"], "continuationSan": ["Qe4+", "Kf7", "Qxf4+"], "continuationText": "56. Qe4+ Kf7 57. Qxf4+", "themes": ["crushing", "endgame", "fork", "short"], "source": "lichess_static"}, {"puzzleId": "N15xt", "fen": "6k1/6r1/6PR/1p2n1KB/8/8/8/8 b - - 1 65", "sideToMove": "b", "pieceCount": 8, "ratingBucket": 1400, "whitePieces": ["Kg5", "Rh6", "Bh5", "Pg6"], "blackPieces": ["Kg8", "Rg7", "Ne5", "Pb5"], "continuationSan": ["Nf7+", "Kf6", "Nxh6"], "continuationText": "65... Nf7+ 66. Kf6 Nxh6", "themes": ["crushing", "endgame", "pin", "short"], "source": "lichess_static"}, {"puzzleId": "1ZLGB", "fen": "8/8/3b4/1pp5/4Pk2/1P1K4/8/6B1 w - - 0 47", "sideToMove": "w", "pieceCount": 8, "ratingBucket": 1400, "whitePieces": ["Kd3", "Bg1", "Pb3", "Pe4"], "blackPieces": ["Kf4", "Bd6", "Pb5", "Pc5"], "continuationSan": ["Bh2+", "Kg5", "Bxd6"], "continuationText": "47. Bh2+ Kg5 48. Bxd6", "themes": ["bishopEndgame", "crushing", "endgame", "short", "skewer"], "source": "lichess_static"}, {"puzzleId": "3KU96", "fen": "8/1k6/1P6/P7/5n2/4pNKp/8/8 w - - 10 53", "sideToMove": "w", "pieceCount": 8, "ratingBucket": 1400, "whitePieces": ["Kg3", "Nf3", "Pa5", "Pb6"], "blackPieces": ["Kb7", "Nf4", "Pe3", "Ph3"], "continuationSan": ["Kxf4", "e2", "Kg3"], "continuationText": "53. Kxf4 e2 54. Kg3", "themes": ["crushing", "endgame", "hangingPiece", "knightEndgame", "short"], "source": "lichess_static"}, {"puzzleId": "TFINx", "fen": "8/1R3p1r/1p5P/1Pk3K1/8/8/8/8 b - - 2 54", "sideToMove": "b", "pieceCount": 8, "ratingBucket": 1400, "whitePieces": ["Kg5", "Rb7", "Pb5", "Ph6"], "blackPieces": ["Kc5", "Rh7", "Pb6", "Pf7"], "continuationSan": ["f6+", "Kg6", "Rxb7"], "continuationText": "54... f6+ 55. Kg6 Rxb7", "themes": ["crushing", "discoveredAttack", "endgame", "rookEndgame", "short"], "source": "lichess_static"}, {"puzzleId": "I8QMr", "fen": "8/P1n5/3k4/8/1P6/N4pp1/8/6K1 w - - 1 64", "sideToMove": "w", "pieceCount": 8, "ratingBucket": 1400, "whitePieces": ["Kg1", "Na3", "Pa7", "Pb4"], "blackPieces": ["Kd6", "Nc7", "Pf3", "Pg3"], "continuationSan": ["Nb5+", "Nxb5", "a8=Q"], "continuationText": "64. Nb5+ Nxb5 65. a8=Q", "themes": ["advancedPawn", "advantage", "deflection", "endgame", "knightEndgame", "promotion", "short"], "source": "lichess_static"}, {"puzzleId": "NqA0G", "fen": "8/8/5kpR/5p2/4r2P/6P1/5K2/8 b - - 0 45", "sideToMove": "b", "pieceCount": 8, "ratingBucket": 1400, "whitePieces": ["Kf2", "Rh6", "Pg3", "Ph4"], "blackPieces": ["Kf6", "Re4", "Pf5", "Pg6"], "continuationSan": ["Kg7", "Rh8", "Kxh8"], "continuationText": "45... Kg7 46. Rh8 Kxh8", "themes": ["crushing", "endgame", "rookEndgame", "short", "trappedPiece"], "source": "lichess_static"}, {"puzzleId": "7E8Nl", "fen": "8/6pk/8/2P4p/4q3/2R3RK/8/8 b - - 8 54", "sideToMove": "b", "pieceCount": 8, "ratingBucket": 1400, "whitePieces": ["Kh3", "Rc3", "Rg3", "Pc5"], "blackPieces": ["Kh7", "Qe4", "Pg7", "Ph5"], "continuationSan": ["Qh1#"], "continuationText": "54... Qh1#", "themes": ["endgame", "mate", "mateIn1", "oneMove", "queenRookEndgame"], "source": "lichess_static"}, {"puzzleId": "SC8xp", "fen": "8/3R3p/4p3/4r1k1/8/6P1/5PK1/8 w - - 0 44", "sideToMove": "w", "pieceCount": 8, "ratingBucket": 1400, "whitePieces": ["Kg2", "Rd7", "Pf2", "Pg3"], "blackPieces": ["Kg5", "Re5", "Pe6", "Ph7"], "continuationSan": ["f4+", "Kg6", "fxe5"], "continuationText": "44. f4+ Kg6 45. fxe5", "themes": ["crushing", "endgame", "fork", "rookEndgame", "short"], "source": "lichess_static"}, {"puzzleId": "JWvZu", "fen": "1r6/8/P4pk1/8/3Q2P1/6K1/1r6/8 b - - 1 50", "sideToMove": "b", "pieceCount": 8, "ratingBucket": 1400, "whitePieces": ["Kg3", "Qd4", "Pa6", "Pg4"], "blackPieces": ["Kg6", "Rb2", "Rb8", "Pf6"], "continuationSan": ["R8b3+", "Kf4", "Rb4"], "continuationText": "50... R8b3+ 51. Kf4 Rb4", "themes": ["crushing", "endgame", "pin", "queenRookEndgame", "short"], "source": "lichess_static"}, {"puzzleId": "7ucH2", "fen": "8/8/4P3/1Q6/8/2k4P/2q3PK/q7 w - - 0 55", "sideToMove": "w", "pieceCount": 8, "ratingBucket": 1400, "whitePieces": ["Kh2", "Qb5", "Pe6", "Pg2", "Ph3"], "blackPieces": ["Kc3", "Qa1", "Qc2"], "continuationSan": ["Qe5+", "Kb4", "Qxa1"], "continuationText": "55. Qe5+ Kb4 56. Qxa1", "themes": ["crushing", "endgame", "queenEndgame", "short", "skewer"], "source": "lichess_static"}, {"puzzleId": "On5IJ", "fen": "8/2Pk4/1R1P4/8/8/8/2rpb3/3K4 w - - 2 51", "sideToMove": "w", "pieceCount": 8, "ratingBucket": 1400, "whitePieces": ["Kd1", "Rb6", "Pc7", "Pd6"], "blackPieces": ["Kd7", "Rc2", "Be2", "Pd2"], "continuationSan": ["Kxe2", "d1=R+", "Kxd1"], "continuationText": "51. Kxe2 d1=R+ 52. Kxd1", "themes": ["crushing", "endgame", "hangingPiece", "short"], "source": "lichess_static"}, {"puzzleId": "DJDfe", "fen": "8/r1p4R/4kp2/8/3K4/5P1P/8/8 b - - 0 36", "sideToMove": "b", "pieceCount": 8, "ratingBucket": 1400, "whitePieces": ["Kd4", "Rh7", "Pf3", "Ph3"], "blackPieces": ["Ke6", "Ra7", "Pc7", "Pf6"], "continuationSan": ["c5+", "Kxc5", "Rxh7"], "continuationText": "36... c5+ 37. Kxc5 Rxh7", "themes": ["crushing", "discoveredAttack", "endgame", "rookEndgame", "short"], "source": "lichess_static"}, {"puzzleId": "1Gyjd", "fen": "8/R7/8/4p3/3p1kP1/5P2/4K3/7r b - - 3 54", "sideToMove": "b", "pieceCount": 8, "ratingBucket": 1400, "whitePieces": ["Ke2", "Ra7", "Pf3", "Pg4"], "blackPieces": ["Kf4", "Rh1", "Pd4", "Pe5"], "continuationSan": ["Rh2+", "Kd3", "Kxf3"], "continuationText": "54... Rh2+ 55. Kd3 Kxf3", "themes": ["advantage", "deflection", "endgame", "rookEndgame", "short"], "source": "lichess_static"}, {"puzzleId": "P1YOD", "fen": "b7/4k3/1P1Np3/3p4/3P4/4K3/8/8 w - - 1 48", "sideToMove": "w", "pieceCount": 8, "ratingBucket": 1400, "whitePieces": ["Ke3", "Nd6", "Pb6", "Pd4"], "blackPieces": ["Ke7", "Ba8", "Pd5", "Pe6"], "continuationSan": ["b7", "Bxb7", "Nxb7"], "continuationText": "48. b7 Bxb7 49. Nxb7", "themes": ["advancedPawn", "crushing", "endgame", "short", "trappedPiece"], "source": "lichess_static"}, {"puzzleId": "UBpL1", "fen": "8/2R3p1/4p3/1K1k1p2/4rP2/8/8/8 w - - 4 65", "sideToMove": "w", "pieceCount": 8, "ratingBucket": 1400, "whitePieces": ["Kb5", "Rc7", "Pf4"], "blackPieces": ["Kd5", "Re4", "Pe6", "Pf5", "Pg7"], "continuationSan": ["Rd7#"], "continuationText": "65. Rd7#", "themes": ["endgame", "mate", "mateIn1", "oneMove", "rookEndgame"], "source": "lichess_static"}, {"puzzleId": "UC8Sc", "fen": "8/8/8/1R6/4kp2/5Np1/1p4K1/1r6 w - - 8 75", "sideToMove": "w", "pieceCount": 8, "ratingBucket": 1400, "whitePieces": ["Kg2", "Rb5", "Nf3"], "blackPieces": ["Ke4", "Rb1", "Pb2", "Pf4", "Pg3"], "continuationSan": ["Nd2+", "Kd3", "Nxb1"], "continuationText": "75. Nd2+ Kd3 76. Nxb1", "themes": ["crushing", "endgame", "fork", "short"], "source": "lichess_static"}, {"puzzleId": "ROOAD", "fen": "8/3Q4/1p4k1/1Pq1p3/3p4/8/8/3K4 w - - 4 60", "sideToMove": "w", "pieceCount": 8, "ratingBucket": 1400, "whitePieces": ["Kd1", "Qd7", "Pb5"], "blackPieces": ["Kg6", "Qc5", "Pb6", "Pd4", "Pe5"], "continuationSan": ["Qc6+", "Kh5", "Qxc5"], "continuationText": "60. Qc6+ Kh5 61. Qxc5", "themes": ["crushing", "endgame", "pin", "queenEndgame", "short"], "source": "lichess_static"}, {"puzzleId": "Inhtw", "fen": "1r6/6R1/3k4/4N3/7P/6PK/8/3r4 w - - 7 56", "sideToMove": "w", "pieceCount": 8, "ratingBucket": 1400, "whitePieces": ["Kh3", "Rg7", "Ne5", "Pg3", "Ph4"], "blackPieces": ["Kd6", "Rb8", "Rd1"], "continuationSan": ["Rd7+", "Kxe5", "Rxd1"], "continuationText": "56. Rd7+ Kxe5 57. Rxd1", "themes": ["crushing", "endgame", "short", "skewer"], "source": "lichess_static"}, {"puzzleId": "7rZl0", "fen": "8/8/1P5p/6p1/5R2/4p1k1/3pK3/8 b - - 0 46", "sideToMove": "b", "pieceCount": 8, "ratingBucket": 1400, "whitePieces": ["Ke2", "Rf4", "Pb6"], "blackPieces": ["Kg3", "Pd2", "Pe3", "Pg5", "Ph6"], "continuationSan": ["gxf4", "b7", "f3+"], "continuationText": "46... gxf4 47. b7 f3+", "themes": ["crushing", "endgame", "hangingPiece", "short"], "source": "lichess_static"}, {"puzzleId": "85OfL", "fen": "8/8/3k4/2r1p2R/5P2/3K2PP/8/8 b - - 0 49", "sideToMove": "b", "pieceCount": 8, "ratingBucket": 1400, "whitePieces": ["Kd3", "Rh5", "Pf4", "Pg3", "Ph3"], "blackPieces": ["Kd6", "Rc5", "Pe5"], "continuationSan": ["e4+", "Kxe4", "Rxh5"], "continuationText": "49... e4+ 50. Kxe4 Rxh5", "themes": ["crushing", "discoveredAttack", "endgame", "rookEndgame", "short"], "source": "lichess_static"}, {"puzzleId": "Yehnh", "fen": "1R6/8/7k/6pp/7P/2r2PK1/8/8 w - - 0 58", "sideToMove": "w", "pieceCount": 8, "ratingBucket": 1400, "whitePieces": ["Kg3", "Rb8", "Pf3", "Ph4"], "blackPieces": ["Kh6", "Rc3", "Pg5", "Ph5"], "continuationSan": ["Rb6+", "Kh7", "hxg5"], "continuationText": "58. Rb6+ Kh7 59. hxg5", "themes": ["crushing", "deflection", "endgame", "rookEndgame", "short"], "source": "lichess_static"}, {"puzzleId": "T4mol", "fen": "1Nb5/8/3k1K2/3p1p2/3P1P2/8/8/8 b - - 15 73", "sideToMove": "b", "pieceCount": 8, "ratingBucket": 1400, "whitePieces": ["Kf6", "Nb8", "Pd4", "Pf4"], "blackPieces": ["Kd6", "Bc8", "Pd5", "Pf5"], "continuationSan": ["Kc7", "Na6+", "Bxa6"], "continuationText": "73... Kc7 74. Na6+ Bxa6", "themes": ["crushing", "endgame", "short", "trappedPiece"], "source": "lichess_static"}, {"puzzleId": "MIRS3", "fen": "8/1k6/1p4R1/pK4P1/P4r2/8/8/8 b - - 2 64", "sideToMove": "b", "pieceCount": 8, "ratingBucket": 1400, "whitePieces": ["Kb5", "Rg6", "Pa4", "Pg5"], "blackPieces": ["Kb7", "Rf4", "Pa5", "Pb6"], "continuationSan": ["Rb4#"], "continuationText": "64... Rb4#", "themes": ["endgame", "mate", "mateIn1", "oneMove", "rookEndgame"], "source": "lichess_static"}, {"puzzleId": "5zDBa", "fen": "8/4kp2/7R/4P3/8/2q3B1/5P2/6K1 b - - 1 41", "sideToMove": "b", "pieceCount": 8, "ratingBucket": 1400, "whitePieces": ["Kg1", "Rh6", "Bg3", "Pe5", "Pf2"], "blackPieces": ["Ke7", "Qc3", "Pf7"], "continuationSan": ["Qc1+", "Kg2", "Qxh6"], "continuationText": "41... Qc1+ 42. Kg2 Qxh6", "themes": ["crushing", "endgame", "fork", "short"], "source": "lichess_static"}, {"puzzleId": "AJ7iU", "fen": "4k3/4b2R/4P2p/3P3r/2K5/8/8/8 w - - 6 62", "sideToMove": "w", "pieceCount": 8, "ratingBucket": 1400, "whitePieces": ["Kc4", "Rh7", "Pd5", "Pe6"], "blackPieces": ["Ke8", "Rh5", "Be7", "Ph6"], "continuationSan": ["Rh8+", "Bf8", "d6"], "continuationText": "62. Rh8+ Bf8 63. d6", "themes": ["crushing", "endgame", "pin", "short"], "source": "lichess_static"}, {"puzzleId": "QgNMS", "fen": "5B2/8/p4k1P/1p2n3/1P6/8/5K2/8 w - - 0 45", "sideToMove": "w", "pieceCount": 8, "ratingBucket": 1400, "whitePieces": ["Kf2", "Bf8", "Pb4", "Ph6"], "blackPieces": ["Kf6", "Ne5", "Pa6", "Pb5"], "continuationSan": ["Bg7+", "Kg6", "Bxe5"], "continuationText": "45. Bg7+ Kg6 46. Bxe5", "themes": ["crushing", "deflection", "endgame", "short", "skewer"], "source": "lichess_static"}, {"puzzleId": "PG1Wi", "fen": "8/4kp2/1P1N4/6n1/5pP1/8/7K/8 b - - 0 33", "sideToMove": "b", "pieceCount": 8, "ratingBucket": 1400, "whitePieces": ["Kh2", "Nd6", "Pb6", "Pg4"], "blackPieces": ["Ke7", "Ng5", "Pf4", "Pf7"], "continuationSan": ["Kxd6", "b7", "Kc7"], "continuationText": "33... Kxd6 34. b7 Kc7", "themes": ["crushing", "endgame", "hangingPiece", "knightEndgame", "short"], "source": "lichess_static"}, {"puzzleId": "F3CdR", "fen": "8/1Q6/2N2b2/5p2/8/5K2/2k2P2/2q5 w - - 2 52", "sideToMove": "w", "pieceCount": 8, "ratingBucket": 1400, "whitePieces": ["Kf3", "Qb7", "Nc6", "Pf2"], "blackPieces": ["Kc2", "Qc1", "Bf6", "Pf5"], "continuationSan": ["Nb4+", "Kb1", "Nd3+"], "continuationText": "52. Nb4+ Kb1 53. Nd3+", "themes": ["crushing", "discoveredAttack", "discoveredCheck", "endgame", "short"], "source": "lichess_static"}, {"puzzleId": "AIgjc", "fen": "R7/8/8/3p4/5P2/3k1KP1/p3r3/8 w - - 0 52", "sideToMove": "w", "pieceCount": 8, "ratingBucket": 1400, "whitePieces": ["Kf3", "Ra8", "Pf4", "Pg3"], "blackPieces": ["Kd3", "Re2", "Pa2", "Pd5"], "continuationSan": ["Ra3+", "Kc4", "Kxe2"], "continuationText": "52. Ra3+ Kc4 53. Kxe2", "themes": ["crushing", "deflection", "endgame", "rookEndgame", "short"], "source": "lichess_static"}, {"puzzleId": "OBVAH", "fen": "8/8/4k3/5p1N/4pK2/4P1P1/5n2/8 b - - 7 62", "sideToMove": "b", "pieceCount": 8, "ratingBucket": 1400, "whitePieces": ["Kf4", "Nh5", "Pe3", "Pg3"], "blackPieces": ["Ke6", "Nf2", "Pe4", "Pf5"], "continuationSan": ["Nh3#"], "continuationText": "62... Nh3#", "themes": ["endgame", "knightEndgame", "mate", "mateIn1", "oneMove"], "source": "lichess_static"}, {"puzzleId": "J4bAu", "fen": "8/5k2/8/5n2/5B2/R5p1/2r3P1/5K2 b - - 3 61", "sideToMove": "b", "pieceCount": 8, "ratingBucket": 1400, "whitePieces": ["Kf1", "Ra3", "Bf4", "Pg2"], "blackPieces": ["Kf7", "Rc2", "Nf5", "Pg3"], "continuationSan": ["Rf2+", "Ke1", "Rxf4"], "continuationText": "61... Rf2+ 62. Ke1 Rxf4", "themes": ["crushing", "endgame", "fork", "short"], "source": "lichess_static"}, {"puzzleId": "UC4VB", "fen": "8/6p1/6kp/4p3/4r3/R7/4B1K1/8 w - - 0 54", "sideToMove": "w", "pieceCount": 8, "ratingBucket": 1400, "whitePieces": ["Kg2", "Ra3", "Be2"], "blackPieces": ["Kg6", "Re4", "Pe5", "Pg7", "Ph6"], "continuationSan": ["Bd3", "Kg5", "Bxe4"], "continuationText": "54. Bd3 Kg5 55. Bxe4", "themes": ["crushing", "endgame", "pin", "short"], "source": "lichess_static"}, {"puzzleId": "85qXA", "fen": "8/8/8/2n1q3/p3p3/P1k5/8/5QK1 w - - 0 61", "sideToMove": "w", "pieceCount": 8, "ratingBucket": 1400, "whitePieces": ["Kg1", "Qf1", "Pa3"], "blackPieces": ["Kc3", "Qe5", "Nc5", "Pa4", "Pe4"], "continuationSan": ["Qa1+", "Kd3", "Qxe5"], "continuationText": "61. Qa1+ Kd3 62. Qxe5", "themes": ["crushing", "endgame", "short", "skewer"], "source": "lichess_static"}, {"puzzleId": "WrrKY", "fen": "8/5k2/8/4B1pp/4Pb2/5K1P/8/8 b - - 14 47", "sideToMove": "b", "pieceCount": 8, "ratingBucket": 1400, "whitePieces": ["Kf3", "Be5", "Pe4", "Ph3"], "blackPieces": ["Kf7", "Bf4", "Pg5", "Ph5"], "continuationSan": ["Bxe5", "h4", "g4+"], "continuationText": "47... Bxe5 48. h4 g4+", "themes": ["bishopEndgame", "crushing", "endgame", "hangingPiece", "short"], "source": "lichess_static"}, {"puzzleId": "GpfSp", "fen": "1R6/8/1B6/1r4kp/1P6/8/2n3K1/8 w - - 3 50", "sideToMove": "w", "pieceCount": 8, "ratingBucket": 1400, "whitePieces": ["Kg2", "Rb8", "Bb6", "Pb4"], "blackPieces": ["Kg5", "Rb5", "Nc2", "Ph5"], "continuationSan": ["Bd8+", "Kg6", "Rxb5"], "continuationText": "50. Bd8+ Kg6 51. Rxb5", "themes": ["crushing", "discoveredAttack", "endgame", "short"], "source": "lichess_static"}, {"puzzleId": "PWG45", "fen": "8/8/6p1/pk6/2R5/2K2P1P/6r1/8 b - - 0 50", "sideToMove": "b", "pieceCount": 8, "ratingBucket": 1400, "whitePieces": ["Kc3", "Rc4", "Pf3", "Ph3"], "blackPieces": ["Kb5", "Rg2", "Pa5", "Pg6"], "continuationSan": ["Rc2+", "Kxc2", "Kxc4"], "continuationText": "50... Rc2+ 51. Kxc2 Kxc4", "themes": ["crushing", "deflection", "endgame", "rookEndgame", "short"], "source": "lichess_static"}, {"puzzleId": "81rcz", "fen": "8/8/5Qrk/8/5P1P/5B1K/5q2/8 w - - 4 107", "sideToMove": "w", "pieceCount": 8, "ratingBucket": 1400, "whitePieces": ["Kh3", "Qf6", "Bf3", "Pf4", "Ph4"], "blackPieces": ["Kh6", "Qf2", "Rg6"], "continuationSan": ["Qh8#"], "continuationText": "107. Qh8#", "themes": ["endgame", "mate", "mateIn1", "oneMove"], "source": "lichess_static"}, {"puzzleId": "1P6Yg", "fen": "8/8/R5pp/4N1k1/5p2/3K4/7r/8 w - - 0 35", "sideToMove": "w", "pieceCount": 8, "ratingBucket": 1400, "whitePieces": ["Kd3", "Ra6", "Ne5"], "blackPieces": ["Kg5", "Rh2", "Pf4", "Pg6", "Ph6"], "continuationSan": ["Nf3+", "Kg4", "Nxh2+"], "continuationText": "35. Nf3+ Kg4 36. Nxh2+", "themes": ["crushing", "endgame", "fork", "short"], "source": "lichess_static"}, {"puzzleId": "148h9", "fen": "8/8/R7/3p1p2/1b2k1p1/1P6/4K3/8 w - - 1 49", "sideToMove": "w", "pieceCount": 8, "ratingBucket": 1400, "whitePieces": ["Ke2", "Ra6", "Pb3"], "blackPieces": ["Ke4", "Bb4", "Pd5", "Pf5", "Pg4"], "continuationSan": ["Ra4", "d4", "Rxb4"], "continuationText": "49. Ra4 d4 50. Rxb4", "themes": ["crushing", "endgame", "pin", "short"], "source": "lichess_static"}, {"puzzleId": "J2rRJ", "fen": "8/p2Q3p/2K5/8/P7/1q3k2/3b4/8 w - - 4 57", "sideToMove": "w", "pieceCount": 8, "ratingBucket": 1400, "whitePieces": ["Kc6", "Qd7", "Pa4"], "blackPieces": ["Kf3", "Qb3", "Bd2", "Pa7", "Ph7"], "continuationSan": ["Qh3+", "Ke4", "Qxb3"], "continuationText": "57. Qh3+ Ke4 58. Qxb3", "themes": ["crushing", "endgame", "short", "skewer"], "source": "lichess_static"}, {"puzzleId": "LNplE", "fen": "8/2k5/8/5K2/5P2/3NRn1p/6r1/8 w - - 0 54", "sideToMove": "w", "pieceCount": 8, "ratingBucket": 1400, "whitePieces": ["Kf5", "Re3", "Nd3", "Pf4"], "blackPieces": ["Kc7", "Rg2", "Nf3", "Ph3"], "continuationSan": ["Rxf3", "h2", "Rh3"], "continuationText": "54. Rxf3 h2 55. Rh3", "themes": ["advantage", "endgame", "hangingPiece", "short"], "source": "lichess_static"}, {"puzzleId": "8Gqsx", "fen": "8/8/2R3Pk/1p6/1rp4K/8/6P1/8 b - - 0 49", "sideToMove": "b", "pieceCount": 8, "ratingBucket": 1400, "whitePieces": ["Kh4", "Rc6", "Pg2", "Pg6"], "blackPieces": ["Kh6", "Rb4", "Pb5", "Pc4"], "continuationSan": ["c3+", "g4", "Rc4"], "continuationText": "49... c3+ 50. g4 Rc4", "themes": ["clearance", "crushing", "discoveredAttack", "discoveredCheck", "endgame", "rookEndgame", "short"], "source": "lichess_static"}, {"puzzleId": "0PHsb", "fen": "8/p7/7P/5r2/4k1K1/3p4/p7/R7 w - - 3 55", "sideToMove": "w", "pieceCount": 8, "ratingBucket": 1400, "whitePieces": ["Kg4", "Ra1", "Ph6"], "blackPieces": ["Ke4", "Rf5", "Pa2", "Pa7", "Pd3"], "continuationSan": ["Re1+", "Kd5", "Kxf5"], "continuationText": "55. Re1+ Kd5 56. Kxf5", "themes": ["crushing", "deflection", "endgame", "rookEndgame", "short"], "source": "lichess_static"}, {"puzzleId": "HoUKY", "fen": "8/1B6/6p1/6k1/3P4/4KR2/r7/2n5 b - - 8 53", "sideToMove": "b", "pieceCount": 8, "ratingBucket": 1400, "whitePieces": ["Ke3", "Rf3", "Bb7", "Pd4"], "blackPieces": ["Kg5", "Ra2", "Nc1", "Pg6"], "continuationSan": ["Re2#"], "continuationText": "53... Re2#", "themes": ["endgame", "mate", "mateIn1", "oneMove"], "source": "lichess_static"}, {"puzzleId": "4X0Bn", "fen": "8/6k1/2R5/3B2qP/6p1/8/5PK1/8 w - - 2 56", "sideToMove": "w", "pieceCount": 8, "ratingBucket": 1400, "whitePieces": ["Kg2", "Rc6", "Bd5", "Pf2", "Ph5"], "blackPieces": ["Kg7", "Qg5", "Pg4"], "continuationSan": ["Rg6+", "Qxg6", "hxg6"], "continuationText": "56. Rg6+ Qxg6 57. hxg6", "themes": ["crushing", "endgame", "fork", "short"], "source": "lichess_static"}, {"puzzleId": "SXJmC", "fen": "8/6bk/6p1/2p5/2Q3K1/8/Pr6/8 b - - 1 42", "sideToMove": "b", "pieceCount": 8, "ratingBucket": 1400, "whitePieces": ["Kg4", "Qc4", "Pa2"], "blackPieces": ["Kh7", "Rb2", "Bg7", "Pc5", "Pg6"], "continuationSan": ["Rb4", "Qxb4", "cxb4"], "continuationText": "42... Rb4 43. Qxb4 cxb4", "themes": ["crushing", "endgame", "pin", "short"], "source": "lichess_static"}, {"puzzleId": "TDE4E", "fen": "8/6k1/5nP1/R5KP/8/P7/8/7r b - - 6 61", "sideToMove": "b", "pieceCount": 8, "ratingBucket": 1400, "whitePieces": ["Kg5", "Ra5", "Pa3", "Pg6", "Ph5"], "blackPieces": ["Kg7", "Rh1", "Nf6"], "continuationSan": ["Rxh5+", "Kf4", "Rxa5"], "continuationText": "61... Rxh5+ 62. Kf4 Rxa5", "themes": ["crushing", "endgame", "short", "skewer"], "source": "lichess_static"}, {"puzzleId": "RdxPX", "fen": "8/8/p6P/P7/8/2Bb4/3Kpk2/8 w - - 5 58", "sideToMove": "w", "pieceCount": 8, "ratingBucket": 1400, "whitePieces": ["Kd2", "Bc3", "Pa5", "Ph6"], "blackPieces": ["Kf2", "Bd3", "Pa6", "Pe2"], "continuationSan": ["Kxd3", "e1=Q", "Bxe1+"], "continuationText": "58. Kxd3 e1=Q 59. Bxe1+", "themes": ["bishopEndgame", "crushing", "endgame", "hangingPiece", "short"], "source": "lichess_static"}, {"puzzleId": "Ua7RS", "fen": "8/8/6k1/8/r4p1R/7P/4KPP1/8 b - - 3 43", "sideToMove": "b", "pieceCount": 8, "ratingBucket": 1400, "whitePieces": ["Ke2", "Rh4", "Pf2", "Pg2", "Ph3"], "blackPieces": ["Kg6", "Ra4", "Pf4"], "continuationSan": ["f3+", "Kxf3", "Rxh4"], "continuationText": "43... f3+ 44. Kxf3 Rxh4", "themes": ["crushing", "discoveredAttack", "endgame", "rookEndgame", "short"], "source": "lichess_static"}, {"puzzleId": "V6gfp", "fen": "1k6/R6P/6K1/8/1p1P4/8/p6r/8 w - - 1 58", "sideToMove": "w", "pieceCount": 8, "ratingBucket": 1400, "whitePieces": ["Kg6", "Ra7", "Pd4", "Ph7"], "blackPieces": ["Kb8", "Rh2", "Pa2", "Pb4"], "continuationSan": ["Rxa2", "Rxa2", "h8=Q+"], "continuationText": "58. Rxa2 Rxa2 59. h8=Q+", "themes": ["advancedPawn", "crushing", "deflection", "endgame", "promotion", "rookEndgame", "short"], "source": "lichess_static"}, {"puzzleId": "0Ftzc", "fen": "6k1/R4p2/7K/4B3/5P2/5b2/6r1/8 b - - 0 36", "sideToMove": "b", "pieceCount": 8, "ratingBucket": 1400, "whitePieces": ["Kh6", "Ra7", "Be5", "Pf4"], "blackPieces": ["Kg8", "Rg2", "Bf3", "Pf7"], "continuationSan": ["Rg6#"], "continuationText": "36... Rg6#", "themes": ["endgame", "mate", "mateIn1", "oneMove", "pillsburysMate"], "source": "lichess_static"}, {"puzzleId": "YvNKT", "fen": "8/1p2r1k1/p2R3p/5P2/5K2/8/8/8 w - - 8 45", "sideToMove": "w", "pieceCount": 8, "ratingBucket": 1400, "whitePieces": ["Kf4", "Rd6", "Pf5"], "blackPieces": ["Kg7", "Re7", "Pa6", "Pb7", "Ph6"], "continuationSan": ["f6+", "Kf8", "fxe7+"], "continuationText": "45. f6+ Kf8 46. fxe7+", "themes": ["advancedPawn", "crushing", "endgame", "fork", "rookEndgame", "short"], "source": "lichess_static"}, {"puzzleId": "Zae2J", "fen": "8/8/6k1/6B1/2R1b2P/1K6/2p1r3/8 b - - 3 94", "sideToMove": "b", "pieceCount": 8, "ratingBucket": 1400, "whitePieces": ["Kb3", "Rc4", "Bg5", "Ph4"], "blackPieces": ["Kg6", "Re2", "Be4", "Pc2"], "continuationSan": ["Bd5", "Kb4", "Bxc4"], "continuationText": "94... Bd5 95. Kb4 Bxc4", "themes": ["crushing", "endgame", "pin", "short"], "source": "lichess_static"}, {"puzzleId": "QzVIZ", "fen": "8/8/5N2/1p5R/2n2PK1/1r2k3/8/8 w - - 5 63", "sideToMove": "w", "pieceCount": 8, "ratingBucket": 1400, "whitePieces": ["Kg4", "Rh5", "Nf6", "Pf4"], "blackPieces": ["Ke3", "Rb3", "Nc4", "Pb5"], "continuationSan": ["Rh3+", "Kd4", "Rxb3"], "continuationText": "63. Rh3+ Kd4 64. Rxb3", "themes": ["crushing", "endgame", "short", "skewer"], "source": "lichess_static"}, {"puzzleId": "COBwL", "fen": "8/8/4p3/4kp2/8/2p4R/1pr5/1K6 w - - 0 65", "sideToMove": "w", "pieceCount": 8, "ratingBucket": 1400, "whitePieces": ["Kb1", "Rh3"], "blackPieces": ["Ke5", "Rc2", "Pb2", "Pc3", "Pe6", "Pf5"], "continuationSan": ["Kxc2", "Ke4", "Rxc3"], "continuationText": "65. Kxc2 Ke4 66. Rxc3", "themes": ["capturingDefender", "crushing", "endgame", "hangingPiece", "rookEndgame", "short"], "source": "lichess_static"}, {"puzzleId": "YWtnv", "fen": "6k1/5R2/8/4KN2/4Pr2/P7/5r2/8 w - - 1 51", "sideToMove": "w", "pieceCount": 8, "ratingBucket": 1400, "whitePieces": ["Ke5", "Rf7", "Nf5", "Pa3", "Pe4"], "blackPieces": ["Kg8", "Rf2", "Rf4"], "continuationSan": ["Nh6+", "Kh8", "Rxf4"], "continuationText": "51. Nh6+ Kh8 52. Rxf4", "themes": ["crushing", "discoveredAttack", "endgame", "short"], "source": "lichess_static"}, {"puzzleId": "1NX0j", "fen": "8/r2Pk3/p1K5/5n2/8/8/6p1/6R1 w - - 5 60", "sideToMove": "w", "pieceCount": 8, "ratingBucket": 1400, "whitePieces": ["Kc6", "Rg1", "Pd7"], "blackPieces": ["Ke7", "Ra7", "Nf5", "Pa6", "Pg2"], "continuationSan": ["Re1+", "Kf7", "d8=Q"], "continuationText": "60. Re1+ Kf7 61. d8=Q", "themes": ["advancedPawn", "advantage", "deflection", "endgame", "promotion", "short"], "source": "lichess_static"}, {"puzzleId": "OG8LB", "fen": "R7/8/8/P5b1/3B4/2P2k2/r7/4K3 b - - 0 60", "sideToMove": "b", "pieceCount": 8, "ratingBucket": 1400, "whitePieces": ["Ke1", "Ra8", "Bd4", "Pa5", "Pc3"], "blackPieces": ["Kf3", "Ra2", "Bg5"], "continuationSan": ["Ra1#"], "continuationText": "60... Ra1#", "themes": ["endgame", "mate", "mateIn1", "oneMove", "pillsburysMate"], "source": "lichess_static"}, {"puzzleId": "Xx0Q5", "fen": "8/4k3/2P2p2/1n3K2/p1B5/5P2/8/8 b - - 1 47", "sideToMove": "b", "pieceCount": 8, "ratingBucket": 1400, "whitePieces": ["Kf5", "Bc4", "Pc6", "Pf3"], "blackPieces": ["Ke7", "Nb5", "Pa4", "Pf6"], "continuationSan": ["Nd6+", "Kf4", "Nxc4"], "continuationText": "47... Nd6+ 48. Kf4 Nxc4", "themes": ["crushing", "endgame", "fork", "short"], "source": "lichess_static"}, {"puzzleId": "Ucbbo", "fen": "8/8/4k2p/4P2P/4r1NK/8/6P1/8 b - - 1 54", "sideToMove": "b", "pieceCount": 8, "ratingBucket": 1400, "whitePieces": ["Kh4", "Ng4", "Pe5", "Pg2", "Ph5"], "blackPieces": ["Ke6", "Re4", "Ph6"], "continuationSan": ["Kf5", "Kg3", "Rxg4+"], "continuationText": "54... Kf5 55. Kg3 Rxg4+", "themes": ["crushing", "endgame", "pin", "short"], "source": "lichess_static"}, {"puzzleId": "08Fo5", "fen": "8/5bp1/5k1p/5P2/6PK/4B3/8/8 w - - 1 41", "sideToMove": "w", "pieceCount": 8, "ratingBucket": 1400, "whitePieces": ["Kh4", "Be3", "Pf5", "Pg4"], "blackPieces": ["Kf6", "Bf7", "Pg7", "Ph6"], "continuationSan": ["Bd4+", "Ke7", "Bxg7"], "continuationText": "41. Bd4+ Ke7 42. Bxg7", "themes": ["bishopEndgame", "crushing", "deflection", "endgame", "short", "skewer"], "source": "lichess_static"}, {"puzzleId": "ROHPc", "fen": "8/8/3n3p/5K2/4N3/3p3P/2k3P1/8 w - - 10 60", "sideToMove": "w", "pieceCount": 8, "ratingBucket": 1400, "whitePieces": ["Kf5", "Ne4", "Pg2", "Ph3"], "blackPieces": ["Kc2", "Nd6", "Pd3", "Ph6"], "continuationSan": ["Nxd6", "d2", "Nc4"], "continuationText": "60. Nxd6 d2 61. Nc4", "themes": ["crushing", "endgame", "hangingPiece", "knightEndgame", "short"], "source": "lichess_static"}, {"puzzleId": "DU9uB", "fen": "8/8/1r3p1R/6p1/4K3/6P1/6kP/8 b - - 1 57", "sideToMove": "b", "pieceCount": 8, "ratingBucket": 1400, "whitePieces": ["Ke4", "Rh6", "Pg3", "Ph2"], "blackPieces": ["Kg2", "Rb6", "Pf6", "Pg5"], "continuationSan": ["f5+", "Kxf5", "Rxh6"], "continuationText": "57... f5+ 58. Kxf5 Rxh6", "themes": ["crushing", "discoveredAttack", "endgame", "rookEndgame", "short"], "source": "lichess_static"}, {"puzzleId": "Q6p2A", "fen": "4r3/PK6/6p1/8/5k2/8/4p2P/4R3 w - - 1 48", "sideToMove": "w", "pieceCount": 8, "ratingBucket": 1400, "whitePieces": ["Kb7", "Re1", "Pa7", "Ph2"], "blackPieces": ["Kf4", "Re8", "Pe2", "Pg6"], "continuationSan": ["Rxe2", "Rxe2", "a8=Q"], "continuationText": "48. Rxe2 Rxe2 49. a8=Q", "themes": ["advancedPawn", "advantage", "deflection", "endgame", "promotion", "rookEndgame", "short"], "source": "lichess_static"}, {"puzzleId": "EA0TI", "fen": "3r1k2/7R/5PP1/8/8/4n3/2p5/2K5 w - - 4 59", "sideToMove": "w", "pieceCount": 8, "ratingBucket": 1400, "whitePieces": ["Kc1", "Rh7", "Pf6", "Pg6"], "blackPieces": ["Kf8", "Rd8", "Ne3", "Pc2"], "continuationSan": ["Rh8#"], "continuationText": "59. Rh8#", "themes": ["endgame", "mate", "mateIn1", "oneMove"], "source": "lichess_static"}, {"puzzleId": "R5100", "fen": "8/8/2p5/8/3b2P1/1p5K/1r4Q1/1k6 w - - 8 53", "sideToMove": "w", "pieceCount": 8, "ratingBucket": 1400, "whitePieces": ["Kh3", "Qg2", "Pg4"], "blackPieces": ["Kb1", "Rb2", "Bd4", "Pb3", "Pc6"], "continuationSan": ["Qe4+", "Rc2", "Qxd4"], "continuationText": "53. Qe4+ Rc2 54. Qxd4", "themes": ["crushing", "endgame", "fork", "short"], "source": "lichess_static"}, {"puzzleId": "15dNJ", "fen": "8/4PR2/6p1/8/6KP/3p4/3kr3/8 w - - 0 45", "sideToMove": "w", "pieceCount": 8, "ratingBucket": 1400, "whitePieces": ["Kg4", "Rf7", "Pe7", "Ph4"], "blackPieces": ["Kd2", "Re2", "Pd3", "Pg6"], "continuationSan": ["Rf2", "Rxf2", "e8=Q"], "continuationText": "45. Rf2 Rxf2 46. e8=Q", "themes": ["advancedPawn", "advantage", "deflection", "endgame", "pin", "promotion", "rookEndgame", "short"], "source": "lichess_static"}, {"puzzleId": "Fcnwn", "fen": "8/4k3/5p1Q/8/4PK2/2q5/2P3P1/8 b - - 0 45", "sideToMove": "b", "pieceCount": 8, "ratingBucket": 1400, "whitePieces": ["Kf4", "Qh6", "Pc2", "Pe4", "Pg2"], "blackPieces": ["Ke7", "Qc3", "Pf6"], "continuationSan": ["Qd2+", "Kf3", "Qxh6"], "continuationText": "45... Qd2+ 46. Kf3 Qxh6", "themes": ["crushing", "endgame", "queenEndgame", "short", "skewer"], "source": "lichess_static"}, {"puzzleId": "RnbCW", "fen": "8/8/8/1pb5/6PB/P4Pk1/8/5K2 b - - 0 97", "sideToMove": "b", "pieceCount": 8, "ratingBucket": 1400, "whitePieces": ["Kf1", "Bh4", "Pa3", "Pf3", "Pg4"], "blackPieces": ["Kg3", "Bc5", "Pb5"], "continuationSan": ["Kxh4", "Ke2", "Bxa3"], "continuationText": "97... Kxh4 98. Ke2 Bxa3", "themes": ["bishopEndgame", "crushing", "endgame", "hangingPiece", "short"], "source": "lichess_static"}, {"puzzleId": "2Dd2s", "fen": "8/8/r3p2R/3k4/5K2/2P4P/6P1/8 b - - 0 41", "sideToMove": "b", "pieceCount": 8, "ratingBucket": 1400, "whitePieces": ["Kf4", "Rh6", "Pc3", "Pg2", "Ph3"], "blackPieces": ["Kd5", "Ra6", "Pe6"], "continuationSan": ["e5+", "Kg5", "Rxh6"], "continuationText": "41... e5+ 42. Kg5 Rxh6", "themes": ["crushing", "discoveredAttack", "endgame", "rookEndgame", "short"], "source": "lichess_static"}, {"puzzleId": "G1L15", "fen": "8/8/4pk2/4R3/5K1p/r4P1P/8/8 b - - 0 38", "sideToMove": "b", "pieceCount": 8, "ratingBucket": 1400, "whitePieces": ["Kf4", "Re5", "Pf3", "Ph3"], "blackPieces": ["Kf6", "Ra3", "Pe6", "Ph4"], "continuationSan": ["Rxf3+", "Kxf3", "Kxe5"], "continuationText": "38... Rxf3+ 39. Kxf3 Kxe5", "themes": ["crushing", "deflection", "endgame", "rookEndgame", "short"], "source": "lichess_static"}, {"puzzleId": "Q0F6J", "fen": "3Q4/6k1/5p2/5Kp1/4r1P1/8/5P2/8 b - - 2 45", "sideToMove": "b", "pieceCount": 8, "ratingBucket": 1400, "whitePieces": ["Kf5", "Qd8", "Pf2", "Pg4"], "blackPieces": ["Kg7", "Re4", "Pf6", "Pg5"], "continuationSan": ["Re5#"], "continuationText": "45... Re5#", "themes": ["endgame", "mate", "mateIn1", "oneMove", "queenRookEndgame"], "source": "lichess_static"}, {"puzzleId": "7DjR8", "fen": "8/5Q2/5p1k/6r1/5K2/6P1/pr6/8 w - - 0 60", "sideToMove": "w", "pieceCount": 8, "ratingBucket": 1400, "whitePieces": ["Kf4", "Qf7", "Pg3"], "blackPieces": ["Kh6", "Rb2", "Rg5", "Pa2", "Pf6"], "continuationSan": ["Qxf6+", "Kh7", "Qxb2"], "continuationText": "60. Qxf6+ Kh7 61. Qxb2", "themes": ["crushing", "endgame", "fork", "queenRookEndgame", "short"], "source": "lichess_static"}, {"puzzleId": "3zssq", "fen": "7k/5B2/p6q/8/1P6/P7/6R1/6K1 w - - 0 61", "sideToMove": "w", "pieceCount": 8, "ratingBucket": 1400, "whitePieces": ["Kg1", "Rg2", "Bf7", "Pa3", "Pb4"], "blackPieces": ["Kh8", "Qh6", "Pa6"], "continuationSan": ["Rh2", "Kg7", "Rxh6"], "continuationText": "61. Rh2 Kg7 62. Rxh6", "themes": ["crushing", "endgame", "pin", "short"], "source": "lichess_static"}, {"puzzleId": "0qkvz", "fen": "8/8/R7/2p5/P1k5/r4p2/2K2P2/8 b - - 2 54", "sideToMove": "b", "pieceCount": 8, "ratingBucket": 1400, "whitePieces": ["Kc2", "Ra6", "Pa4", "Pf2"], "blackPieces": ["Kc4", "Ra3", "Pc5", "Pf3"], "continuationSan": ["Ra2+", "Kb1", "Rxf2"], "continuationText": "54... Ra2+ 55. Kb1 Rxf2", "themes": ["crushing", "endgame", "rookEndgame", "short", "skewer"], "source": "lichess_static"}, {"puzzleId": "QIDqy", "fen": "5k2/2R4b/4r2P/4p1P1/8/4K3/8/8 w - - 4 52", "sideToMove": "w", "pieceCount": 8, "ratingBucket": 1400, "whitePieces": ["Ke3", "Rc7", "Pg5", "Ph6"], "blackPieces": ["Kf8", "Re6", "Bh7", "Pe5"], "continuationSan": ["Rxh7", "Kg8", "Rg7+"], "continuationText": "52. Rxh7 Kg8 53. Rg7+", "themes": ["crushing", "endgame", "hangingPiece", "short"], "source": "lichess_static"}, {"puzzleId": "1Yk1H", "fen": "2k5/R1p1r3/8/p3P3/3K4/2P5/8/8 b - - 0 42", "sideToMove": "b", "pieceCount": 8, "ratingBucket": 1400, "whitePieces": ["Kd4", "Ra7", "Pc3", "Pe5"], "blackPieces": ["Kc8", "Re7", "Pa5", "Pc7"], "continuationSan": ["c5+", "Kxc5", "Rxa7"], "continuationText": "42... c5+ 43. Kxc5 Rxa7", "themes": ["crushing", "discoveredAttack", "endgame", "rookEndgame", "short"], "source": "lichess_static"}, {"puzzleId": "QTg3G", "fen": "6k1/5p2/8/8/P1K5/1P6/5r1p/2R5 b - - 0 44", "sideToMove": "b", "pieceCount": 8, "ratingBucket": 1400, "whitePieces": ["Kc4", "Rc1", "Pa4", "Pb3"], "blackPieces": ["Kg8", "Rf2", "Pf7", "Ph2"], "continuationSan": ["Rc2+", "Rxc2", "h1=Q"], "continuationText": "44... Rc2+ 45. Rxc2 h1=Q", "themes": ["advancedPawn", "advantage", "deflection", "endgame", "promotion", "rookEndgame", "short"], "source": "lichess_static"}, {"puzzleId": "6wjQC", "fen": "3R4/3r4/P2P4/8/8/5k1K/5P1B/8 b - - 0 48", "sideToMove": "b", "pieceCount": 8, "ratingBucket": 1400, "whitePieces": ["Kh3", "Rd8", "Bh2", "Pa6", "Pd6", "Pf2"], "blackPieces": ["Kf3", "Rd7"], "continuationSan": ["Rh7#"], "continuationText": "48... Rh7#", "themes": ["endgame", "mate", "mateIn1", "oneMove"], "source": "lichess_static"}, {"puzzleId": "0Bfbo", "fen": "8/5p2/7k/3R4/4KN2/r6P/8/3n4 b - - 14 54", "sideToMove": "b", "pieceCount": 8, "ratingBucket": 1400, "whitePieces": ["Ke4", "Rd5", "Nf4", "Ph3"], "blackPieces": ["Kh6", "Ra3", "Nd1", "Pf7"], "continuationSan": ["Nc3+", "Kf5", "Nxd5"], "continuationText": "54... Nc3+ 55. Kf5 Nxd5", "themes": ["crushing", "endgame", "fork", "short"], "source": "lichess_static"}, {"puzzleId": "SVaZH", "fen": "R7/8/3b3k/7P/8/p1p5/2Kp4/8 w - - 3 57", "sideToMove": "w", "pieceCount": 8, "ratingBucket": 1400, "whitePieces": ["Kc2", "Ra8", "Ph5"], "blackPieces": ["Kh6", "Bd6", "Pa3", "Pc3", "Pd2"], "continuationSan": ["Ra6", "Kxh5", "Rxd6"], "continuationText": "57. Ra6 Kxh5 58. Rxd6", "themes": ["crushing", "endgame", "pin", "short"], "source": "lichess_static"}, {"puzzleId": "KoBFS", "fen": "r7/8/8/8/PRP5/3K2k1/r7/3R4 b - - 0 59", "sideToMove": "b", "pieceCount": 8, "ratingBucket": 1400, "whitePieces": ["Kd3", "Rb4", "Rd1", "Pa4", "Pc4"], "blackPieces": ["Kg3", "Ra2", "Ra8"], "continuationSan": ["Rd8+", "Kc3", "Rxd1"], "continuationText": "59... Rd8+ 60. Kc3 Rxd1", "themes": ["advantage", "endgame", "rookEndgame", "short", "skewer"], "source": "lichess_static"}, {"puzzleId": "B2tJy", "fen": "8/8/p2k4/1p5P/8/2K5/1P3n2/3B4 b - - 0 50", "sideToMove": "b", "pieceCount": 8, "ratingBucket": 1400, "whitePieces": ["Kc3", "Bd1", "Pb2", "Ph5"], "blackPieces": ["Kd6", "Nf2", "Pa6", "Pb5"], "continuationSan": ["Nxd1+", "Kc2", "Ne3+"], "continuationText": "50... Nxd1+ 51. Kc2 Ne3+", "themes": ["crushing", "endgame", "hangingPiece", "short"], "source": "lichess_static"}, {"puzzleId": "TR5ss", "fen": "8/8/4RN1p/4n1k1/6P1/4r3/5K2/8 b - - 3 64", "sideToMove": "b", "pieceCount": 8, "ratingBucket": 1400, "whitePieces": ["Kf2", "Re6", "Nf6", "Pg4"], "blackPieces": ["Kg5", "Re3", "Ne5", "Ph6"], "continuationSan": ["Nxg4+", "Nxg4", "Rxe6"], "continuationText": "64... Nxg4+ 65. Nxg4 Rxe6", "themes": ["crushing", "discoveredAttack", "endgame", "short"], "source": "lichess_static"}, {"puzzleId": "LQZ7p", "fen": "8/8/2P2B2/6p1/5p1k/5P1b/7K/8 w - - 0 53", "sideToMove": "w", "pieceCount": 8, "ratingBucket": 1400, "whitePieces": ["Kh2", "Bf6", "Pc6", "Pf3"], "blackPieces": ["Kh4", "Bh3", "Pf4", "Pg5"], "continuationSan": ["Bxg5+", "Kxg5", "Kxh3"], "continuationText": "53. Bxg5+ Kxg5 54. Kxh3", "themes": ["bishopEndgame", "crushing", "deflection", "endgame", "short"], "source": "lichess_static"}, {"puzzleId": "4ZY07", "fen": "8/4Q2p/6pk/5p2/4qP1K/8/8/8 w - - 20 57", "sideToMove": "w", "pieceCount": 8, "ratingBucket": 1400, "whitePieces": ["Kh4", "Qe7", "Pf4"], "blackPieces": ["Kh6", "Qe4", "Pf5", "Pg6", "Ph7"], "continuationSan": ["Qf8#"], "continuationText": "57. Qf8#", "themes": ["endgame", "mate", "mateIn1", "oneMove", "queenEndgame"], "source": "lichess_static"}]